{
  "openapi": "3.0.0",
  "info": {
    "title": "Example API",
    "version": "1.0.0",
    "description": "A sample API for demonstration purposes"
  },
  "servers": [
    {
      "url": "https://api.example.com",
      "description": "Production server"
    },
    {
      "url": "https://staging-api.example.com",
      "description": "Staging server"
    }
  ],
  "paths": {
    "/users": {
      "get": {
        "summary": "List all users",
        "description": "Retrieve a paginated list of all users",
        "parameters": [
          {
            "name": "page",
            "in": "query",
            "description": "Page number",
            "required": false,
            "schema": {
              "type": "integer",
              "default": 1
            }
          },
          {
            "name": "per_page",
            "in": "query",
            "description": "Items per page",
            "required": false,
            "schema": {
              "type": "integer",
              "default": 20
            }
          }
        ],
        "responses": {
          "200": {
            "description": "Successful response",
            "content": {
              "application/json": {
                "schema": {
                  "type": "object",
                  "properties": {
                    "users": {
                      "type": "array",
                      "items": {
                        "$ref": "#/components/schemas/User"
                      }
                    },
                    "pagination": {
                      "$ref": "#/components/schemas/Pagination"
                    }
                  }
                }
              }
            }
          }
        }
      },
      "post": {
        "summary": "Create a new user",
        "description": "Create a new user account",
        "requestBody": {
          "required": true,
          "content": {
            "application/json": {
              "schema": {
                "$ref": "#/components/schemas/CreateUserRequest"
              }
            }
          }
        },
        "responses": {
          "201": {
            "description": "User created successfully",
            "content": {
              "application/json": {
                "schema": {
                  "$ref": "#/components/schemas/User"
                }
              }
            }
          },
          "400": {
            "description": "Bad request",
            "content": {
              "application/json": {
                "schema": {
                  "$ref": "#/components/schemas/Error"
                }
              }
            }
          }
        }
      }
    },
    "/users/{id}": {
      "get": {
        "summary": "Get user by ID",
        "description": "Retrieve a specific user by their ID",
        "parameters": [
          {
            "name": "id",
            "in": "path",
            "required": true,
            "description": "User ID",
            "schema": {
              "type": "integer"
            }
          }
        ],
        "responses": {
          "200": {
            "description": "Successful response",
            "content": {
              "application/json": {
                "schema": {
                  "$ref": "#/components/schemas/User"
                }
              }
            }
          },
          "404": {
            "description": "User not found",
            "content": {
              "application/json": {
                "schema": {
                  "$ref": "#/components/schemas/Error"
                }
              }
            }
          }
        }
      },
      "delete": {
        "summary": "Delete a user",
        "description": "Permanently delete a user account",
        "parameters": [
          {
            "name": "id",
            "in": "path",
            "required": true,
            "description": "User ID",
            "schema": {
              "type": "integer"
            }
          }
        ],
        "responses": {
          "204": {
            "description": "User deleted successfully"
          },
          "404": {
            "description": "User not found"
          }
        }
      }
    }
  },
  "components": {
    "schemas": {
      "User": {
        "type": "object",
        "properties": {
          "id": {
            "type": "integer",
            "description": "User ID"
          },
          "name": {
            "type": "string",
            "description": "User's full name"
          },
          "email": {
            "type": "string",
            "format": "email",
            "description": "User's email address"
          },
          "created_at": {
            "type": "string",
            "format": "date-time",
            "description": "Account creation timestamp"
          }
        }
      },
      "CreateUserRequest": {
        "type": "object",
        "required": ["name", "email"],
        "properties": {
          "name": {
            "type": "string",
            "description": "User's full name"
          },
          "email": {
            "type": "string",
            "format": "email",
            "description": "User's email address"
          }
        }
      },
      "Pagination": {
        "type": "object",
        "properties": {
          "page": {
            "type": "integer"
          },
          "per_page": {
            "type": "integer"
          },
          "total": {
            "type": "integer"
          }
        }
      },
      "Error": {
        "type": "object",
        "properties": {
          "error": {
            "type": "string",
            "description": "Error message"
          },
          "code": {
            "type": "string",
            "description": "Error code"
          }
        }
      }
    }
  }
}

